{
  "zone activity" : {
    "transaction" : "zone activity",
    "sampleCount" : 5,
    "errorCount" : 0,
    "errorPct" : 0.0,
    "meanResTime" : 165.8,
    "medianResTime" : 167.0,
    "minResTime" : 150.0,
    "maxResTime" : 183.0,
    "pct1ResTime" : 183.0,
    "pct2ResTime" : 183.0,
    "pct3ResTime" : 183.0,
    "throughput" : 2.1240441801189465,
    "receivedKBytesPerSec" : 590.7626480193288,
    "sentKBytesPerSec" : 0.6928034728122344
  },
  "Total" : {
    "transaction" : "Total",
    "sampleCount" : 15,
    "errorCount" : 0,
    "errorPct" : 0.0,
    "meanResTime" : 183.6,
    "medianResTime" : 104.0,
    "minResTime" : 31.0,
    "maxResTime" : 1162.0,
    "pct1ResTime" : 618.4000000000003,
    "pct2ResTime" : 1162.0,
    "pct3ResTime" : 1162.0,
    "throughput" : 3.581661891117479,
    "receivedKBytesPerSec" : 333.7845387864136,
    "sentKBytesPerSec" : 1.0224991792024833
  },
  "login" : {
    "transaction" : "login",
    "sampleCount" : 5,
    "errorCount" : 0,
    "errorPct" : 0.0,
    "meanResTime" : 342.6,
    "medianResTime" : 104.0,
    "minResTime" : 95.0,
    "maxResTime" : 1162.0,
    "pct1ResTime" : 1162.0,
    "pct2ResTime" : 1162.0,
    "pct3ResTime" : 1162.0,
    "throughput" : 1.25,
    "receivedKBytesPerSec" : 0.97900390625,
    "sentKBytesPerSec" : 0.311279296875
  },
  "create api key" : {
    "transaction" : "create api key",
    "sampleCount" : 5,
    "errorCount" : 0,
    "errorPct" : 0.0,
    "meanResTime" : 42.4,
    "medianResTime" : 35.0,
    "minResTime" : 31.0,
    "maxResTime" : 57.0,
    "pct1ResTime" : 57.0,
    "pct2ResTime" : 57.0,
    "pct3ResTime" : 57.0,
    "throughput" : 2.200704225352113,
    "receivedKBytesPerSec" : 1.4605454995598592,
    "sentKBytesPerSec" : 0.6189480633802817
  }
}