<?xml version="1.0" encoding="UTF-8"?>
<testResults version="1.2">
<httpSample t="402" it="0" lt="399" ct="314" ts="1766069583954" s="true" lb="login" rc="200" rm="OK" tn="zone activity 1-1" dt="text" by="802" sby="255" ng="1" na="1">
  <assertionResult>
    <name>Duration Assertion</name>
    <failure>false</failure>
    <error>false</error>
  </assertionResult>
  <java.net.URL>https://qa.kwant.ai/api/login%20</java.net.URL>
</httpSample>
<httpSample t="67" it="0" lt="67" ct="0" ts="1766069584876" s="true" lb="create api key" rc="200" rm="OK" tn="zone activity 1-1" dt="text" by="680" sby="288" ng="2" na="2">
  <assertionResult>
    <name>Duration Assertion</name>
    <failure>false</failure>
    <error>false</error>
  </assertionResult>
  <java.net.URL>https://qa.kwant.ai/api/apiuser</java.net.URL>
</httpSample>
<httpSample t="203" it="0" lt="203" ct="125" ts="1766069584882" s="true" lb="login" rc="200" rm="OK" tn="zone activity 1-2" dt="text" by="802" sby="255" ng="2" na="2">
  <assertionResult>
    <name>Duration Assertion</name>
    <failure>false</failure>
    <error>false</error>
  </assertionResult>
  <java.net.URL>https://qa.kwant.ai/api/login%20</java.net.URL>
</httpSample>
<httpSample t="66" it="0" lt="66" ct="0" ts="1766069585088" s="true" lb="create api key" rc="200" rm="OK" tn="zone activity 1-2" dt="text" by="680" sby="288" ng="2" na="2">
  <assertionResult>
    <name>Duration Assertion</name>
    <failure>false</failure>
    <error>false</error>
  </assertionResult>
  <java.net.URL>https://qa.kwant.ai/api/apiuser</java.net.URL>
</httpSample>
<httpSample t="326" it="0" lt="170" ct="0" ts="1766069584959" s="true" lb="zone activity" rc="200" rm="OK" tn="zone activity 1-1" dt="text" by="284896" sby="334" ng="2" na="2">
  <assertionResult>
    <name>Duration Assertion</name>
    <failure>false</failure>
    <error>false</error>
  </assertionResult>
  <assertionResult>
    <name>Response Assertion</name>
    <failure>false</failure>
    <error>false</error>
  </assertionResult>
  <assertionResult>
    <name>Duration Assertion</name>
    <failure>false</failure>
    <error>false</error>
  </assertionResult>
  <java.net.URL>https://qa.kwant.ai/api/open/v2/zoneActivity?size=9999&amp;page=&amp;startDate=2025-12-01&amp;endDate=2025-12-14</java.net.URL>
</httpSample>
<httpSample t="323" it="0" lt="165" ct="0" ts="1766069585155" s="true" lb="zone activity" rc="200" rm="OK" tn="zone activity 1-2" dt="text" by="284864" sby="334" ng="1" na="1">
  <assertionResult>
    <name>Duration Assertion</name>
    <failure>false</failure>
    <error>false</error>
  </assertionResult>
  <assertionResult>
    <name>Response Assertion</name>
    <failure>false</failure>
    <error>false</error>
  </assertionResult>
  <assertionResult>
    <name>Duration Assertion</name>
    <failure>false</failure>
    <error>false</error>
  </assertionResult>
  <java.net.URL>https://qa.kwant.ai/api/open/v2/zoneActivity?size=9999&amp;page=&amp;startDate=2025-12-01&amp;endDate=2025-12-14</java.net.URL>
</httpSample>
<httpSample t="194" it="0" lt="194" ct="115" ts="1766069585881" s="true" lb="login" rc="200" rm="OK" tn="zone activity 1-3" dt="text" by="802" sby="255" ng="1" na="1">
  <assertionResult>
    <name>Duration Assertion</name>
    <failure>false</failure>
    <error>false</error>
  </assertionResult>
  <java.net.URL>https://qa.kwant.ai/api/login%20</java.net.URL>
</httpSample>
<httpSample t="67" it="0" lt="67" ct="0" ts="1766069586077" s="true" lb="create api key" rc="200" rm="OK" tn="zone activity 1-3" dt="text" by="680" sby="288" ng="1" na="1">
  <assertionResult>
    <name>Duration Assertion</name>
    <failure>false</failure>
    <error>false</error>
  </assertionResult>
  <java.net.URL>https://qa.kwant.ai/api/apiuser</java.net.URL>
</httpSample>
<httpSample t="327" it="0" lt="168" ct="0" ts="1766069586145" s="true" lb="zone activity" rc="200" rm="OK" tn="zone activity 1-3" dt="text" by="284920" sby="334" ng="1" na="1">
  <assertionResult>
    <name>Duration Assertion</name>
    <failure>false</failure>
    <error>false</error>
  </assertionResult>
  <assertionResult>
    <name>Response Assertion</name>
    <failure>false</failure>
    <error>false</error>
  </assertionResult>
  <assertionResult>
    <name>Duration Assertion</name>
    <failure>false</failure>
    <error>false</error>
  </assertionResult>
  <java.net.URL>https://qa.kwant.ai/api/open/v2/zoneActivity?size=9999&amp;page=&amp;startDate=2025-12-01&amp;endDate=2025-12-14</java.net.URL>
</httpSample>
<httpSample t="194" it="0" lt="194" ct="116" ts="1766069586881" s="true" lb="login" rc="200" rm="OK" tn="zone activity 1-4" dt="text" by="802" sby="255" ng="1" na="1">
  <assertionResult>
    <name>Duration Assertion</name>
    <failure>false</failure>
    <error>false</error>
  </assertionResult>
  <java.net.URL>https://qa.kwant.ai/api/login%20</java.net.URL>
</httpSample>
<httpSample t="68" it="0" lt="68" ct="0" ts="1766069587076" s="true" lb="create api key" rc="200" rm="OK" tn="zone activity 1-4" dt="text" by="680" sby="288" ng="1" na="1">
  <assertionResult>
    <name>Duration Assertion</name>
    <failure>false</failure>
    <error>false</error>
  </assertionResult>
  <java.net.URL>https://qa.kwant.ai/api/apiuser</java.net.URL>
</httpSample>
<httpSample t="332" it="0" lt="171" ct="0" ts="1766069587145" s="true" lb="zone activity" rc="200" rm="OK" tn="zone activity 1-4" dt="text" by="284864" sby="334" ng="1" na="1">
  <assertionResult>
    <name>Duration Assertion</name>
    <failure>false</failure>
    <error>false</error>
  </assertionResult>
  <assertionResult>
    <name>Response Assertion</name>
    <failure>false</failure>
    <error>false</error>
  </assertionResult>
  <assertionResult>
    <name>Duration Assertion</name>
    <failure>false</failure>
    <error>false</error>
  </assertionResult>
  <java.net.URL>https://qa.kwant.ai/api/open/v2/zoneActivity?size=9999&amp;page=&amp;startDate=2025-12-01&amp;endDate=2025-12-14</java.net.URL>
</httpSample>
<httpSample t="201" it="0" lt="201" ct="120" ts="1766069587881" s="true" lb="login" rc="200" rm="OK" tn="zone activity 1-5" dt="text" by="802" sby="255" ng="1" na="1">
  <assertionResult>
    <name>Duration Assertion</name>
    <failure>false</failure>
    <error>false</error>
  </assertionResult>
  <java.net.URL>https://qa.kwant.ai/api/login%20</java.net.URL>
</httpSample>
<httpSample t="70" it="0" lt="70" ct="0" ts="1766069588084" s="true" lb="create api key" rc="200" rm="OK" tn="zone activity 1-5" dt="text" by="680" sby="288" ng="1" na="1">
  <assertionResult>
    <name>Duration Assertion</name>
    <failure>false</failure>
    <error>false</error>
  </assertionResult>
  <java.net.URL>https://qa.kwant.ai/api/apiuser</java.net.URL>
</httpSample>
<httpSample t="373" it="0" lt="202" ct="0" ts="1766069588155" s="true" lb="zone activity" rc="200" rm="OK" tn="zone activity 1-5" dt="text" by="284856" sby="334" ng="1" na="1">
  <assertionResult>
    <name>Duration Assertion</name>
    <failure>false</failure>
    <error>false</error>
  </assertionResult>
  <assertionResult>
    <name>Response Assertion</name>
    <failure>false</failure>
    <error>false</error>
  </assertionResult>
  <assertionResult>
    <name>Duration Assertion</name>
    <failure>false</failure>
    <error>false</error>
  </assertionResult>
  <java.net.URL>https://qa.kwant.ai/api/open/v2/zoneActivity?size=9999&amp;page=&amp;startDate=2025-12-01&amp;endDate=2025-12-14</java.net.URL>
</httpSample>

</testResults>
