<?xml version="1.0" encoding="UTF-8"?>
<testResults version="1.2">
<httpSample t="382" it="0" lt="378" ct="313" ts="1766195684223" s="true" lb="login" rc="200" rm="OK" tn="zone activity 1-1" dt="text" by="802" sby="255" ng="1" na="1">
  <assertionResult>
    <name>Duration Assertion</name>
    <failure>false</failure>
    <error>false</error>
  </assertionResult>
  <java.net.URL>https://qa.kwant.ai/api/login%20</java.net.URL>
</httpSample>
<httpSample t="53" it="0" lt="53" ct="0" ts="1766195685161" s="true" lb="create api key" rc="200" rm="OK" tn="zone activity 1-1" dt="text" by="679" sby="288" ng="2" na="2">
  <assertionResult>
    <name>Duration Assertion</name>
    <failure>false</failure>
    <error>false</error>
  </assertionResult>
  <java.net.URL>https://qa.kwant.ai/api/apiuser</java.net.URL>
</httpSample>
<httpSample t="173" it="0" lt="173" ct="109" ts="1766195685152" s="true" lb="login" rc="200" rm="OK" tn="zone activity 1-2" dt="text" by="802" sby="255" ng="2" na="2">
  <assertionResult>
    <name>Duration Assertion</name>
    <failure>false</failure>
    <error>false</error>
  </assertionResult>
  <java.net.URL>https://qa.kwant.ai/api/login%20</java.net.URL>
</httpSample>
<httpSample t="53" it="0" lt="53" ct="0" ts="1766195685327" s="true" lb="create api key" rc="200" rm="OK" tn="zone activity 1-2" dt="text" by="679" sby="288" ng="2" na="2">
  <assertionResult>
    <name>Duration Assertion</name>
    <failure>false</failure>
    <error>false</error>
  </assertionResult>
  <java.net.URL>https://qa.kwant.ai/api/apiuser</java.net.URL>
</httpSample>
<httpSample t="272" it="0" lt="145" ct="0" ts="1766195685229" s="true" lb="zone activity" rc="200" rm="OK" tn="zone activity 1-1" dt="text" by="284904" sby="334" ng="2" na="2">
  <assertionResult>
    <name>Duration Assertion</name>
    <failure>false</failure>
    <error>false</error>
  </assertionResult>
  <assertionResult>
    <name>Response Assertion</name>
    <failure>false</failure>
    <error>false</error>
  </assertionResult>
  <assertionResult>
    <name>Duration Assertion</name>
    <failure>false</failure>
    <error>false</error>
  </assertionResult>
  <java.net.URL>https://qa.kwant.ai/api/open/v2/zoneActivity?size=9999&amp;page=&amp;startDate=2025-12-01&amp;endDate=2025-12-14</java.net.URL>
</httpSample>
<httpSample t="285" it="0" lt="145" ct="0" ts="1766195685382" s="true" lb="zone activity" rc="200" rm="OK" tn="zone activity 1-2" dt="text" by="284872" sby="334" ng="1" na="1">
  <assertionResult>
    <name>Duration Assertion</name>
    <failure>false</failure>
    <error>false</error>
  </assertionResult>
  <assertionResult>
    <name>Response Assertion</name>
    <failure>false</failure>
    <error>false</error>
  </assertionResult>
  <assertionResult>
    <name>Duration Assertion</name>
    <failure>false</failure>
    <error>false</error>
  </assertionResult>
  <java.net.URL>https://qa.kwant.ai/api/open/v2/zoneActivity?size=9999&amp;page=&amp;startDate=2025-12-01&amp;endDate=2025-12-14</java.net.URL>
</httpSample>
<httpSample t="156" it="0" lt="156" ct="97" ts="1766195686152" s="true" lb="login" rc="200" rm="OK" tn="zone activity 1-3" dt="text" by="802" sby="255" ng="1" na="1">
  <assertionResult>
    <name>Duration Assertion</name>
    <failure>false</failure>
    <error>false</error>
  </assertionResult>
  <java.net.URL>https://qa.kwant.ai/api/login%20</java.net.URL>
</httpSample>
<httpSample t="51" it="0" lt="51" ct="0" ts="1766195686310" s="true" lb="create api key" rc="200" rm="OK" tn="zone activity 1-3" dt="text" by="679" sby="288" ng="1" na="1">
  <assertionResult>
    <name>Duration Assertion</name>
    <failure>false</failure>
    <error>false</error>
  </assertionResult>
  <java.net.URL>https://qa.kwant.ai/api/apiuser</java.net.URL>
</httpSample>
<httpSample t="270" it="0" lt="141" ct="0" ts="1766195686363" s="true" lb="zone activity" rc="200" rm="OK" tn="zone activity 1-3" dt="text" by="284848" sby="334" ng="1" na="1">
  <assertionResult>
    <name>Duration Assertion</name>
    <failure>false</failure>
    <error>false</error>
  </assertionResult>
  <assertionResult>
    <name>Response Assertion</name>
    <failure>false</failure>
    <error>false</error>
  </assertionResult>
  <assertionResult>
    <name>Duration Assertion</name>
    <failure>false</failure>
    <error>false</error>
  </assertionResult>
  <java.net.URL>https://qa.kwant.ai/api/open/v2/zoneActivity?size=9999&amp;page=&amp;startDate=2025-12-01&amp;endDate=2025-12-14</java.net.URL>
</httpSample>
<httpSample t="155" it="0" lt="155" ct="95" ts="1766195687151" s="true" lb="login" rc="200" rm="OK" tn="zone activity 1-4" dt="text" by="802" sby="255" ng="1" na="1">
  <assertionResult>
    <name>Duration Assertion</name>
    <failure>false</failure>
    <error>false</error>
  </assertionResult>
  <java.net.URL>https://qa.kwant.ai/api/login%20</java.net.URL>
</httpSample>
<httpSample t="51" it="0" lt="51" ct="0" ts="1766195687308" s="true" lb="create api key" rc="200" rm="OK" tn="zone activity 1-4" dt="text" by="679" sby="288" ng="1" na="1">
  <assertionResult>
    <name>Duration Assertion</name>
    <failure>false</failure>
    <error>false</error>
  </assertionResult>
  <java.net.URL>https://qa.kwant.ai/api/apiuser</java.net.URL>
</httpSample>
<httpSample t="267" it="0" lt="140" ct="0" ts="1766195687361" s="true" lb="zone activity" rc="200" rm="OK" tn="zone activity 1-4" dt="text" by="284888" sby="334" ng="1" na="1">
  <assertionResult>
    <name>Duration Assertion</name>
    <failure>false</failure>
    <error>false</error>
  </assertionResult>
  <assertionResult>
    <name>Response Assertion</name>
    <failure>false</failure>
    <error>false</error>
  </assertionResult>
  <assertionResult>
    <name>Duration Assertion</name>
    <failure>false</failure>
    <error>false</error>
  </assertionResult>
  <java.net.URL>https://qa.kwant.ai/api/open/v2/zoneActivity?size=9999&amp;page=&amp;startDate=2025-12-01&amp;endDate=2025-12-14</java.net.URL>
</httpSample>
<httpSample t="155" it="0" lt="155" ct="95" ts="1766195688151" s="true" lb="login" rc="200" rm="OK" tn="zone activity 1-5" dt="text" by="802" sby="255" ng="1" na="1">
  <assertionResult>
    <name>Duration Assertion</name>
    <failure>false</failure>
    <error>false</error>
  </assertionResult>
  <java.net.URL>https://qa.kwant.ai/api/login%20</java.net.URL>
</httpSample>
<httpSample t="51" it="0" lt="51" ct="0" ts="1766195688308" s="true" lb="create api key" rc="200" rm="OK" tn="zone activity 1-5" dt="text" by="679" sby="288" ng="1" na="1">
  <assertionResult>
    <name>Duration Assertion</name>
    <failure>false</failure>
    <error>false</error>
  </assertionResult>
  <java.net.URL>https://qa.kwant.ai/api/apiuser</java.net.URL>
</httpSample>
<httpSample t="272" it="0" lt="142" ct="0" ts="1766195688360" s="true" lb="zone activity" rc="200" rm="OK" tn="zone activity 1-5" dt="text" by="284878" sby="334" ng="1" na="1">
  <assertionResult>
    <name>Duration Assertion</name>
    <failure>false</failure>
    <error>false</error>
  </assertionResult>
  <assertionResult>
    <name>Response Assertion</name>
    <failure>false</failure>
    <error>false</error>
  </assertionResult>
  <assertionResult>
    <name>Duration Assertion</name>
    <failure>false</failure>
    <error>false</error>
  </assertionResult>
  <java.net.URL>https://qa.kwant.ai/api/open/v2/zoneActivity?size=9999&amp;page=&amp;startDate=2025-12-01&amp;endDate=2025-12-14</java.net.URL>
</httpSample>

</testResults>
